rubinobot/__init__.py
rubinobot/client.py
rubinobot/methods.py
rubinobot-2.1.dist-info/LICENSE
rubinobot-2.1.dist-info/METADATA
rubinobot-2.1.dist-info/WHEEL
rubinobot-2.1.dist-info/top_level.txt
rubinobot-2.1.dist-info/RECORD
