Metadata-Version: 2.1
Name: rubinobot
Version: 2.1
Summary: Robinobot is a library for building self-robots in Robino based on API
Home-page: https://github.com/activate-sh
Author: Amirali Irvany
Author-email: dev.amirali.irvany@gmail.com
Keywords: bot,Bot,rubino,rubika,rubinobot
Classifier: Programming Language :: Python :: 3
Classifier: License :: OSI Approved :: MIT License
Requires-Python: ~=3.6
License-File: LICENSE
Requires-Dist: requests
